emaps/COPYING
emaps/README.md
emaps/__config__.py
emaps/__init__.py
emaps/__version__.py
emaps/license.txt
emaps/diffract/__init__.py
emaps/diffract/emaps_sims.cp37-win_amd64.pyd
emaps/diffract/libiomp5md.dll
emaps/scattering/__init__.py
emaps/scattering/scattering.cp37-win_amd64.pyd
emaps/spg/__init__.py
emaps/spg/spg.cp37-win_amd64.pyd
emaps/stem4d/LicenseSpring.dll
emaps/stem4d/_stem4d.cp37-win_amd64.pyd
emaps/stem4d/ediom.py
emaps/stem4d/libcrypto-3-x64.dll
emaps/stem4d/libcurl.dll
emaps/stem4d/libssl-3-x64.dll
emaps/stem4d/send.py
emaps/stem4d/stem4d.py
emaps-1.0.8.dist-info/COPYING
emaps-1.0.8.dist-info/METADATA
emaps-1.0.8.dist-info/WHEEL
emaps-1.0.8.dist-info/license.txt
emaps-1.0.8.dist-info/top_level.txt
emaps-1.0.8.dist-info/RECORD
