Metadata-Version: 2.1
Name: emaps
Version: 1.0.8
Summary: Transmission Electron Diffraction Simulations and Crystallographic Computing Engines For pyEMAPS
Home-page: https://www.emlabsolutions.com
Author: EMLab Solutions, Inc.
Author-email: support@emlabsoftware.com
License: Free for using with pyEMAPS
Keywords: Transmission,Electron,Diffraction,Simulation,Crystallography,Python
Classifier: Development Status :: 5 - Production/Stable
Classifier: Programming Language :: Python :: 3.7
Classifier: Operating System :: Microsoft :: Windows
Classifier: Topic :: Software Development :: Libraries :: Python Modules
Classifier: Intended Audience :: Science/Research
Requires-Python: >=3.7
License-File: license.txt
License-File: COPYING
Requires-Dist: msvc-runtime (==14.29.30133)
